CongLingdaoYiShixianMarblesZichanGuanlixitongFabricSdkNode/README.md
CongLingdaoYiShixianMarblesZichanGuanlixitongFabricSdkNode/__init__.py
CongLingdaoYiShixianMarblesZichanGuanlixitongFabricSdkNode/__main__.py
CongLingdaoYiShixianMarblesZichanGuanlixitongFabricSdkNode/file.epub
CongLingdaoYiShixianMarblesZichanGuanlixitongFabricSdkNode/index.html
CongLingdaoYiShixianMarblesZichanGuanlixitongFabricSdkNode/css/__init__.py
CongLingdaoYiShixianMarblesZichanGuanlixitongFabricSdkNode/css/annotations.css
CongLingdaoYiShixianMarblesZichanGuanlixitongFabricSdkNode/css/main.css
CongLingdaoYiShixianMarblesZichanGuanlixitongFabricSdkNode/css/normalize.css
CongLingdaoYiShixianMarblesZichanGuanlixitongFabricSdkNode/css/popup.css
CongLingdaoYiShixianMarblesZichanGuanlixitongFabricSdkNode/font/__init__.py
CongLingdaoYiShixianMarblesZichanGuanlixitongFabricSdkNode/font/fontello.eot
CongLingdaoYiShixianMarblesZichanGuanlixitongFabricSdkNode/font/fontello.svg
CongLingdaoYiShixianMarblesZichanGuanlixitongFabricSdkNode/font/fontello.ttf
CongLingdaoYiShixianMarblesZichanGuanlixitongFabricSdkNode/font/fontello.woff
CongLingdaoYiShixianMarblesZichanGuanlixitongFabricSdkNode/img/__init__.py
CongLingdaoYiShixianMarblesZichanGuanlixitongFabricSdkNode/img/annotator-glyph-sprite.png
CongLingdaoYiShixianMarblesZichanGuanlixitongFabricSdkNode/img/annotator-icon-sprite.png
CongLingdaoYiShixianMarblesZichanGuanlixitongFabricSdkNode/img/apple-touch-icon.png
CongLingdaoYiShixianMarblesZichanGuanlixitongFabricSdkNode/img/cancelfullscreen.png
CongLingdaoYiShixianMarblesZichanGuanlixitongFabricSdkNode/img/close.png
CongLingdaoYiShixianMarblesZichanGuanlixitongFabricSdkNode/img/fullscreen.png
CongLingdaoYiShixianMarblesZichanGuanlixitongFabricSdkNode/img/loader.gif
CongLingdaoYiShixianMarblesZichanGuanlixitongFabricSdkNode/img/menu-icon.png
CongLingdaoYiShixianMarblesZichanGuanlixitongFabricSdkNode/img/save.png
CongLingdaoYiShixianMarblesZichanGuanlixitongFabricSdkNode/img/saved.png
cong_lingdao_yi_shixian_marbles_zichan_guanlixitong_fabric_sdk_node-2024.3.5.0.dist-info/METADATA
cong_lingdao_yi_shixian_marbles_zichan_guanlixitong_fabric_sdk_node-2024.3.5.0.dist-info/WHEEL
cong_lingdao_yi_shixian_marbles_zichan_guanlixitong_fabric_sdk_node-2024.3.5.0.dist-info/entry_points.txt
cong_lingdao_yi_shixian_marbles_zichan_guanlixitong_fabric_sdk_node-2024.3.5.0.dist-info/top_level.txt
cong_lingdao_yi_shixian_marbles_zichan_guanlixitong_fabric_sdk_node-2024.3.5.0.dist-info/RECORD
